setup.py
qjqqjq/__init__.py
qjqqjq/qjqqjq.py
qjqqjq.egg-info/PKG-INFO
qjqqjq.egg-info/SOURCES.txt
qjqqjq.egg-info/dependency_links.txt
qjqqjq.egg-info/requires.txt
qjqqjq.egg-info/top_level.txt