Metadata-Version: 1.0
Name: qjqqjq
Version: 2.1.4
Summary: An feature extraction algorithm
Home-page: https://github.com/WolverineQin/qjqqjq
Author: qjqqjq
Author-email: 1102692995@qq.com
License: MIT Licence
Keywords: pip,qjqqjq,featureextraction
Platform: any
